example_app/__init__.py
example_app/example.py
old_pipelines_trainning-0.0.23.dist-info/METADATA
old_pipelines_trainning-0.0.23.dist-info/WHEEL
old_pipelines_trainning-0.0.23.dist-info/top_level.txt
old_pipelines_trainning-0.0.23.dist-info/RECORD
