Metadata-Version: 2.1
Name: old-pipelines-trainning
Version: 0.0.23
Summary: A small example package
Author: JuanMaTB
Author-email: jm.torrado.borrachero@gmail.com
Requires-Python: >=3.9
Requires-Dist: coloredlogs
